guitartuner/._guitartuner_windows.py.swp
guitartuner/LICENSE
guitartuner/README.md
guitartuner/__init__.py
guitartuner/_guitartuner.py
guitartuner/_guitartuner_windows.py
guitartuner/demo.gif
guitartuner/iconguitar.png
guitartuner/myguitargui.py
guitartuner/mytools.py
guitartuner/notefreq.pkl
guitartuner/screenshot.png
guitartuner/starttuner.py
guitartuner-0.0.3.dist-info/METADATA
guitartuner-0.0.3.dist-info/WHEEL
guitartuner-0.0.3.dist-info/entry_points.txt
guitartuner-0.0.3.dist-info/licenses/LICENSE
guitartuner-0.0.3.dist-info/RECORD
