Metadata-Version: 2.3
Name: guitartuner
Version: 0.0.3
Summary: A tuner app written in python to tune guitars.
Project-URL: Homepage, https://github.com/jithesh82/guitartuner
Project-URL: Bug Tracker, https://github.com/jithesh82/guitartuner
Author-email: Jithesh Kuyyalil <jithesh82@gmail.com>
License-File: LICENSE
Classifier: License :: OSI Approved :: MIT License
Classifier: Operating System :: OS Independent
Classifier: Programming Language :: Python :: 3
Requires-Python: >=3.7
